denoising_diffusion_pytorch/__init__.py
denoising_diffusion_pytorch/attend.py
denoising_diffusion_pytorch/classifier_free_guidance.py
denoising_diffusion_pytorch/continuous_time_gaussian_diffusion.py
denoising_diffusion_pytorch/denoising_diffusion_pytorch.py
denoising_diffusion_pytorch/denoising_diffusion_pytorch_1d.py
denoising_diffusion_pytorch/elucidated_diffusion.py
denoising_diffusion_pytorch/fid_evaluation.py
denoising_diffusion_pytorch/guided_diffusion.py
denoising_diffusion_pytorch/karras_unet.py
denoising_diffusion_pytorch/karras_unet_1d.py
denoising_diffusion_pytorch/karras_unet_3d.py
denoising_diffusion_pytorch/learned_gaussian_diffusion.py
denoising_diffusion_pytorch/repaint.py
denoising_diffusion_pytorch/simple_diffusion.py
denoising_diffusion_pytorch/v_param_continuous_time_gaussian_diffusion.py
denoising_diffusion_pytorch/version.py
denoising_diffusion_pytorch/weighted_objective_gaussian_diffusion.py
denoising_diffusion_pytorch-2.2.4.dist-info/licenses/LICENSE
denoising_diffusion_pytorch-2.2.4.dist-info/METADATA
denoising_diffusion_pytorch-2.2.4.dist-info/WHEEL
denoising_diffusion_pytorch-2.2.4.dist-info/top_level.txt
denoising_diffusion_pytorch-2.2.4.dist-info/RECORD
