Metadata-Version: 2.4
Name: denoising-diffusion-pytorch
Version: 2.2.4
Summary: Denoising Diffusion Probabilistic Models - Pytorch
Home-page: https://github.com/lucidrains/denoising-diffusion-pytorch
Author: Phil Wang
Author-email: lucidrains@gmail.com
License: MIT
Keywords: artificial intelligence,generative models
Classifier: Development Status :: 4 - Beta
Classifier: Intended Audience :: Developers
Classifier: Topic :: Scientific/Engineering :: Artificial Intelligence
Classifier: License :: OSI Approved :: MIT License
Classifier: Programming Language :: Python :: 3.6
License-File: LICENSE
Requires-Dist: accelerate
Requires-Dist: einops
Requires-Dist: ema-pytorch>=0.4.2
Requires-Dist: numpy
Requires-Dist: pillow
Requires-Dist: pytorch-fid
Requires-Dist: scipy
Requires-Dist: torch>=2.0
Requires-Dist: torchvision
Requires-Dist: tqdm
Dynamic: author
Dynamic: author-email
Dynamic: classifier
Dynamic: description-content-type
Dynamic: home-page
Dynamic: keywords
Dynamic: license
Dynamic: license-file
Dynamic: requires-dist
Dynamic: summary
